Metadata-Version: 2.1
Name: hello-world-vitzhdanov
Version: 0.0.1
Summary: A Hello World package
Home-page: https://github.com/ericjaychi/sample-pypi-package
Author: Eric Chi
Author-email: i@zhdanov-1.ru
License: UNKNOWN
Platform: UNKNOWN
Classifier: Programming Language :: Python :: 3.8
Classifier: License :: OSI Approved :: MIT License
Classifier: Operating System :: OS Independent
Requires-Python: >=3.6
License-File: LICENSE
